moonlight/__init__.py
moonlight/jar/python-all.jar
moonlight-0.3.1.dist-info/LICENSE
moonlight-0.3.1.dist-info/METADATA
moonlight-0.3.1.dist-info/WHEEL
moonlight-0.3.1.dist-info/RECORD
