Metadata-Version: 2.1
Name: moonlight
Version: 0.3.1
Summary: Moonlight python wrapper
Author: Ennio Visconti
Author-email: ennio.visconti@gmail.com
Requires-Python: >=3.8,<4.0
Classifier: Programming Language :: Python :: 3
Classifier: Programming Language :: Python :: 3.8
Classifier: Programming Language :: Python :: 3.9
Classifier: Programming Language :: Python :: 3.10
Classifier: Programming Language :: Python :: 3.11
Classifier: Programming Language :: Python :: 3.12
Requires-Dist: pyjnius (>=1.4.2,<2.0.0)
